harrix_test_package/__init__.py
harrix_test_package/functions.py
harrix_test_package-0.8.dist-info/METADATA
harrix_test_package-0.8.dist-info/WHEEL
harrix_test_package-0.8.dist-info/entry_points.txt
harrix_test_package-0.8.dist-info/licenses/LICENSE.md
harrix_test_package-0.8.dist-info/RECORD
