Metadata-Version: 2.4
Name: harrix-test-package
Version: 0.8
Summary: Test package
Project-URL: Homepage, https://github.com/Harrix/harrix-test-package
Author-email: Anton Sergienko <anton.b.sergienko@gmail.com>
License: # The MIT License
License-File: LICENSE.md
Requires-Python: >=3.13
Requires-Dist: numpy>=2.2.1
